{
  "project_info": {
    "project_number": "840320465373",
    "project_id": "deep-plant-demo",
    "storage_bucket": "deep-plant-demo.appspot.com"
  },
  "client": [
    {
      "client_info": {
        "mobilesdk_app_id": "1:840320465373:android:8c09553a2277c6a1621e34",
        "android_client_info": {
          "package_name": "com.example.deep_plant_1"
        }
      },
      "oauth_client": [
        {
          "client_id": "840320465373-p8akrn443uv2kjeagrn73tvlu9m1lcvg.apps.googleusercontent.com",
          "client_type": 3
        }
      ],
      "api_key": [
        {
          "current_key": "AIzaSyCe0dxWmbKNRqJgzCUUuaNN6tuwCqxS4Eg"
        }
      ],
      "services": {
        "appinvite_service": {
          "other_platform_oauth_client": [
            {
              "client_id": "840320465373-p8akrn443uv2kjeagrn73tvlu9m1lcvg.apps.googleusercontent.com",
              "client_type": 3
            }
          ]
        }
      }
    }
  ],
  "configuration_version": "1"
}